lunarapi/__init__.py
lunarapi/api.py
lunarapi/endpoints.py
lunarapi/models.py
lunarapi-1.12.3.dist-info/LICENSE
lunarapi-1.12.3.dist-info/METADATA
lunarapi-1.12.3.dist-info/WHEEL
lunarapi-1.12.3.dist-info/RECORD
