Metadata-Version: 2.1
Name: lunarapi
Version: 1.12.3
Summary: Wrapper for the Lunar API
Home-page: https://pypi.org/project/lunarapi/
Keywords: discord,api,wrapper
Author: WinterFe
Author-email: winter@lunardev.group
Requires-Python: >=3.8,<4.0
Classifier: Programming Language :: Python :: 3
Classifier: Programming Language :: Python :: 3.8
Classifier: Programming Language :: Python :: 3.9
Classifier: Programming Language :: Python :: 3.10
Classifier: Programming Language :: Python :: 3.11
Requires-Dist: Pillow (>=9.2.0,<10.0.0)
Requires-Dist: aiohttp (>=3.6.0,<4)
Requires-Dist: python-dotenv (>=0.20.0,<0.21.0)
Requires-Dist: typing-extensions (>=4.1.0,<4.3.0) ; python_version >= "3.8" and python_version < "3.9"
Project-URL: Documentation, https://docs.lunardev.group/
